viztree/__init__.py
viztree/__main__.py
viztree/argments.py
viztree/templates/dir_tree_html.j2
viztree-0.2.1.dist-info/LICENSE
viztree-0.2.1.dist-info/METADATA
viztree-0.2.1.dist-info/WHEEL
viztree-0.2.1.dist-info/entry_points.txt
viztree-0.2.1.dist-info/top_level.txt
viztree-0.2.1.dist-info/RECORD
