Metadata-Version: 2.1
Name: viztree
Version: 0.2.1
Summary: Directory tree visualizer
Home-page: https://github.com/sky-joker/viztree
Author: sky-joker
Author-email: sky.jokerxx@gmail.com
Maintainer: sky-joker
Maintainer-email: sky.jokerxx@gmail.com
License: MIT
Project-URL: Bug Tracker, https://github.com/sky-joker/viztree/issues
Project-URL: Source Code, https://github.com/sky-joker/viztree
Keywords: tree
Platform: UNKNOWN
Classifier: Environment :: Console
Classifier: License :: OSI Approved :: MIT License
Classifier: Programming Language :: Python :: 3
Classifier: Programming Language :: Python :: 3.6
Classifier: Programming Language :: Python :: 3.7
Classifier: Programming Language :: Python :: 3.8
Classifier: Programming Language :: Python :: 3.9
Requires-Python: >=3.6
Requires-Dist: jinja2
